[
    {
        "name": "Elf (Zendikar)",
        "source": "PSZ",
        "page": 18,
        "size": [
            "M"
        ],
        "speed": 30,
        "ability": [
            {
                "wis": 2
            }
        ],
        "age": {
            "mature": 100,
            "max": 750
        },
        "darkvision": 60,
        "skillProficiencies": [
            {
                "perception": true
            }
        ],
        "languageProficiencies": [
            {
                "common": true,
                "elvish": true
            }
        ],
        "hasFluff": true,
        "slug": "elf__zendikar__psz_generic",
        "display_name": "Elf (Zendikar)",
        "type": "generic",
        "fluff": [
            "**Age:** Although elves reach physical maturity at about the same age as humans, the elven understanding of adulthood goes beyond physical growth to encompass worldly experience. An elf typically claims adulthood and an adult name around the age of 100 and can live to be 750 years old.",
            "",
            "**Alignment:** Elves love freedom, variety, and self-expression, so they lean strongly toward the gentler aspects of chaos. They value and protect others' freedom as well as their own, and they are more often good than not.",
            "",
            "**Size:** Elves range from under 5 to over 6 feet tall and have slender builds. Your size is Medium.",
            "",
            "**Darkvision:** Accustomed to twilit forests and the night sky, you have superior vision in dark and dim conditions. You can see in dim light within 60 feet of you as if it were bright light, and in darkness as if it were dim light. You can't discern color in darkness, only shades of gray.",
            "",
            "**Keen Senses:** You have proficiency in the Perception skill.",
            "",
            "**Fey Ancestry:** You have advantage on saving throws against being *charmed*, and magic can't put you to sleep.",
            "",
            "**Languages:** You can speak, read, and write Common and Elvish. Elvish is fluid, with subtle intonations and intricate grammar. Elven literature is rich and varied, and their songs and poems are famous among other races. Many bards learn their language so they can add Elvish ballads to their repertoires.",
            ""
        ]
    },
    {
        "name": "Joraga Nation",
        "source": "PSZ",
        "raceName": "Elf (Zendikar)",
        "raceSource": "PSZ",
        "page": 19,
        "speed": 35,
        "ability": [
            {
                "dex": 1
            }
        ],
        "weaponProficiencies": [
            {
                "longsword|phb": true,
                "shortsword|phb": true,
                "shortbow|phb": true,
                "longbow|phb": true
            }
        ],
        "size": [
            "M"
        ],
        "age": {
            "mature": 100,
            "max": 750
        },
        "darkvision": 60,
        "skillProficiencies": [
            {
                "perception": true
            }
        ],
        "languageProficiencies": [
            {
                "common": true,
                "elvish": true
            }
        ],
        "hasFluff": true,
        "slug": "elf__zendikar__psz_joraga_nation_psz",
        "display_name": "Joraga Nation Elf (Zendikar)",
        "type": "subrace",
        "fluff": [
            "**Age:** Although elves reach physical maturity at about the same age as humans, the elven understanding of adulthood goes beyond physical growth to encompass worldly experience. An elf typically claims adulthood and an adult name around the age of 100 and can live to be 750 years old.",
            "",
            "**Alignment:** Elves love freedom, variety, and self-expression, so they lean strongly toward the gentler aspects of chaos. They value and protect others' freedom as well as their own, and they are more often good than not.",
            "",
            "**Size:** Elves range from under 5 to over 6 feet tall and have slender builds. Your size is Medium.",
            "",
            "**Darkvision:** Accustomed to twilit forests and the night sky, you have superior vision in dark and dim conditions. You can see in dim light within 60 feet of you as if it were bright light, and in darkness as if it were dim light. You can't discern color in darkness, only shades of gray.",
            "",
            "**Keen Senses:** You have proficiency in the Perception skill.",
            "",
            "**Fey Ancestry:** You have advantage on saving throws against being *charmed*, and magic can't put you to sleep.",
            "",
            "**Languages:** You can speak, read, and write Common and Elvish. Elvish is fluid, with subtle intonations and intricate grammar. Elven literature is rich and varied, and their songs and poems are famous among other races. Many bards learn their language so they can add Elvish ballads to their repertoires.",
            "",
            "**Mask of the Wild:** You can attempt to hide even when you are only lightly obscured by foliage, heavy rain, falling snow, mist, and other natural phenomena.",
            "",
            "**Elf Weapon Training:** You have proficiency with the [longsword](/compendium?plugin=dnd_fifth_edition&category=item&fields=%7B%22name%22%3A%20%22longsword%22%2C%20%22source%22%3A%20%22PHB%22%7D), [shortsword](/compendium?plugin=dnd_fifth_edition&category=item&fields=%7B%22name%22%3A%20%22shortsword%22%2C%20%22source%22%3A%20%22PHB%22%7D), [shortbow](/compendium?plugin=dnd_fifth_edition&category=item&fields=%7B%22name%22%3A%20%22shortbow%22%2C%20%22source%22%3A%20%22PHB%22%7D), and [longbow](/compendium?plugin=dnd_fifth_edition&category=item&fields=%7B%22name%22%3A%20%22longbow%22%2C%20%22source%22%3A%20%22PHB%22%7D).",
            "",
            "**Fleet of Foot:** Your ground speed increases to 35 feet.",
            ""
        ]
    },
    {
        "name": "Mul Daya Nation",
        "source": "PSZ",
        "raceName": "Elf (Zendikar)",
        "raceSource": "PSZ",
        "page": 19,
        "ability": [
            {
                "str": 1
            }
        ],
        "darkvision": 120,
        "traitTags": [
            "Sunlight Sensitivity"
        ],
        "weaponProficiencies": [
            {
                "longsword|phb": true,
                "shortsword|phb": true,
                "shortbow|phb": true,
                "longbow|phb": true
            }
        ],
        "additionalSpells": [
            {
                "innate": {
                    "3": {
                        "daily": {
                            "1": [
                                "hex"
                            ]
                        }
                    },
                    "5": {
                        "daily": {
                            "1": [
                                "darkness"
                            ]
                        }
                    }
                },
                "ability": "wis",
                "known": {
                    "1": [
                        "chill touch#c"
                    ]
                }
            }
        ],
        "size": [
            "M"
        ],
        "speed": 30,
        "age": {
            "mature": 100,
            "max": 750
        },
        "skillProficiencies": [
            {
                "perception": true
            }
        ],
        "languageProficiencies": [
            {
                "common": true,
                "elvish": true
            }
        ],
        "hasFluff": true,
        "slug": "elf__zendikar__psz_mul_daya_nation_psz",
        "display_name": "Mul Daya Nation Elf (Zendikar)",
        "type": "subrace",
        "fluff": [
            "**Age:** Although elves reach physical maturity at about the same age as humans, the elven understanding of adulthood goes beyond physical growth to encompass worldly experience. An elf typically claims adulthood and an adult name around the age of 100 and can live to be 750 years old.",
            "",
            "**Alignment:** Elves love freedom, variety, and self-expression, so they lean strongly toward the gentler aspects of chaos. They value and protect others' freedom as well as their own, and they are more often good than not.",
            "",
            "**Size:** Elves range from under 5 to over 6 feet tall and have slender builds. Your size is Medium.",
            "",
            "**Darkvision:** Accustomed to twilit forests and the night sky, you have superior vision in dark and dim conditions. You can see in dim light within 60 feet of you as if it were bright light, and in darkness as if it were dim light. You can't discern color in darkness, only shades of gray.",
            "",
            "**Keen Senses:** You have proficiency in the Perception skill.",
            "",
            "**Fey Ancestry:** You have advantage on saving throws against being *charmed*, and magic can't put you to sleep.",
            "",
            "**Languages:** You can speak, read, and write Common and Elvish. Elvish is fluid, with subtle intonations and intricate grammar. Elven literature is rich and varied, and their songs and poems are famous among other races. Many bards learn their language so they can add Elvish ballads to their repertoires.",
            "",
            "**Mul Daya Magic:** You know the *chill touch* cantrip. When you reach 3rd level, you can cast the *hex* spell once with this trait and regain the ability to do so when you finish a long rest. When you reach 5th level, you can cast the *darkness* spell once with this trait and regain the ability to do so when you finish a long rest. Wisdom is your spellcasting ability for these spells.",
            "",
            "**Superior Darkvision:** Your Darkvision has a radius of 120 feet.",
            "",
            "**Sunlight Sensitivity:** You have disadvantage on attack rolls and on Wisdom (Perception) checks that rely on sight when you, the target of your attack, or whatever you are trying to perceive is in direct sunlight.",
            "",
            "**Elf Weapon Training:** You have proficiency with the [longsword](/compendium?plugin=dnd_fifth_edition&category=item&fields=%7B%22name%22%3A%20%22longsword%22%2C%20%22source%22%3A%20%22PHB%22%7D), [shortsword](/compendium?plugin=dnd_fifth_edition&category=item&fields=%7B%22name%22%3A%20%22shortsword%22%2C%20%22source%22%3A%20%22PHB%22%7D), [shortbow](/compendium?plugin=dnd_fifth_edition&category=item&fields=%7B%22name%22%3A%20%22shortbow%22%2C%20%22source%22%3A%20%22PHB%22%7D), and [longbow](/compendium?plugin=dnd_fifth_edition&category=item&fields=%7B%22name%22%3A%20%22longbow%22%2C%20%22source%22%3A%20%22PHB%22%7D).",
            ""
        ]
    },
    {
        "name": "Tajuru Nation",
        "source": "PSZ",
        "raceName": "Elf (Zendikar)",
        "raceSource": "PSZ",
        "page": 18,
        "ability": [
            {
                "cha": 1
            }
        ],
        "traitTags": [
            "Skill Proficiency",
            "Tool Proficiency"
        ],
        "skillToolLanguageProficiencies": [
            {
                "choose": [
                    {
                        "from": [
                            "anySkill",
                            "anyTool"
                        ],
                        "count": 2
                    }
                ]
            }
        ],
        "size": [
            "M"
        ],
        "speed": 30,
        "age": {
            "mature": 100,
            "max": 750
        },
        "darkvision": 60,
        "skillProficiencies": [
            {
                "perception": true
            }
        ],
        "languageProficiencies": [
            {
                "common": true,
                "elvish": true
            }
        ],
        "hasFluff": true,
        "slug": "elf__zendikar__psz_tajuru_nation_psz",
        "display_name": "Tajuru Nation Elf (Zendikar)",
        "type": "subrace",
        "fluff": [
            "**Age:** Although elves reach physical maturity at about the same age as humans, the elven understanding of adulthood goes beyond physical growth to encompass worldly experience. An elf typically claims adulthood and an adult name around the age of 100 and can live to be 750 years old.",
            "",
            "**Alignment:** Elves love freedom, variety, and self-expression, so they lean strongly toward the gentler aspects of chaos. They value and protect others' freedom as well as their own, and they are more often good than not.",
            "",
            "**Size:** Elves range from under 5 to over 6 feet tall and have slender builds. Your size is Medium.",
            "",
            "**Darkvision:** Accustomed to twilit forests and the night sky, you have superior vision in dark and dim conditions. You can see in dim light within 60 feet of you as if it were bright light, and in darkness as if it were dim light. You can't discern color in darkness, only shades of gray.",
            "",
            "**Keen Senses:** You have proficiency in the Perception skill.",
            "",
            "**Fey Ancestry:** You have advantage on saving throws against being *charmed*, and magic can't put you to sleep.",
            "",
            "**Languages:** You can speak, read, and write Common and Elvish. Elvish is fluid, with subtle intonations and intricate grammar. Elven literature is rich and varied, and their songs and poems are famous among other races. Many bards learn their language so they can add Elvish ballads to their repertoires.",
            "",
            "**Skill Versatility:** You have proficiency with any combination of two other skills or **Tools (phb) - Page 5** of your choice.",
            ""
        ]
    }
]